setup.py
digCityExtractor/__init__.py
digCityExtractor/city_helper.py
digCityExtractor.egg-info/PKG-INFO
digCityExtractor.egg-info/SOURCES.txt
digCityExtractor.egg-info/dependency_links.txt
digCityExtractor.egg-info/requires.txt
digCityExtractor.egg-info/top_level.txt
test/test_city_extractor.py