Metadata-Version: 1.1
Name: digCityExtractor
Version: 0.3.0
Summary: digCityExtractor
Home-page: https://github.com/usc-isi-i2/dig-city-extractor
Author: Vinay Rao Dandin
Author-email: vrdandin@isi.edu
License: UNKNOWN
Download-URL: https://github.com/usc-isi-i2/dig-city-extractor
Platform: UNKNOWN
